mss_python/__init__.py
mss_python/_version.py
mss_python/client.py
mss_python/request/method_names.py
mss_python/request/methods.py
mss_python/request/types_mss.py
mss_python-0.2.1.dist-info/LICENSE
mss_python-0.2.1.dist-info/METADATA
mss_python-0.2.1.dist-info/WHEEL
mss_python-0.2.1.dist-info/top_level.txt
mss_python-0.2.1.dist-info/RECORD
