Metadata-Version: 2.1
Name: mss-python
Version: 0.2.1
Summary: MSS API wrapper for Python projects
Author: Rubin Canaj
Author-email: HGV <development@hgv.it>
License: MIT License
Project-URL: Repository, https://github.com/bookingsuedtirol/mss-python
Requires-Python: <4,>=3.7
License-File: LICENSE
Requires-Dist: xmltodict ==0.13.0
